coincidence/__init__.py
coincidence/fixtures.py
coincidence/params.py
coincidence/py.typed
coincidence/regressions.py
coincidence/selectors.py
coincidence/utils.py
coincidence-0.6.6.dist-info/LICENSE
coincidence-0.6.6.dist-info/METADATA
coincidence-0.6.6.dist-info/WHEEL
coincidence-0.6.6.dist-info/entry_points.txt
coincidence-0.6.6.dist-info/RECORD
